README.md
map_maker.py
setup.py
address2img.egg-info/PKG-INFO
address2img.egg-info/SOURCES.txt
address2img.egg-info/dependency_links.txt
address2img.egg-info/top_level.txt
testing/__init__.py
testing/test.py