Metadata-Version: 2.1
Name: address2img
Version: 1.1
Summary: A module to convert addresses to images using mapnik
Home-page: https://github.com/marmig0404/address2img
Author: Martin Miglio
Author-email: marmig0404@gmail.com
License: UNKNOWN
Platform: UNKNOWN
Classifier: Programming Language :: Python :: 2.7
